pyxtb/__init__.py
pyxtb/_types.py
pyxtb/api.py
pyxtb/errors.py
pyxtb-1.0.0.post1.dist-info/LICENCE
pyxtb-1.0.0.post1.dist-info/METADATA
pyxtb-1.0.0.post1.dist-info/WHEEL
pyxtb-1.0.0.post1.dist-info/RECORD
