Metadata-Version: 2.1
Name: pyxtb
Version: 1.0.0.post1
Summary: Python wrapper for XTB HTTP API
License: MIT
Keywords: xtb,finance,stock
Author: Michal Karol
Author-email: michal.p.karol@gmail.com
Requires-Python: >=3.12,<4.0
Classifier: Development Status :: 4 - Beta
Classifier: Intended Audience :: Developers
Classifier: Intended Audience :: Financial and Insurance Industry
Classifier: License :: OSI Approved :: MIT License
Classifier: Programming Language :: Python :: 3
Classifier: Programming Language :: Python :: 3.12
Classifier: Programming Language :: Python :: 3.13
Classifier: Programming Language :: Python :: 3.11
Classifier: Topic :: Office/Business :: Financial
Requires-Dist: dataclasses-json (>=0.6.7,<0.7.0)
Requires-Dist: ruff (>=0.7.0,<0.8.0)
Project-URL: Documentation, https://michalkarol.github.io/pyxtb/
Project-URL: Homepage, https://michalkarol.github.io/pyxtb/
Project-URL: Issues, https://github.com/MichalKarol/pyxtb/issues
Project-URL: Repository, https://github.com/MichalKarol/pyxtb
Project-URL: Releases, https://github.com/MichalKarol/pyxtb/releases
